odata_query/__init__.py
odata_query/ast.py
odata_query/django/__init__.py
odata_query/django/django_q.py
odata_query/django/django_q_ext.py
odata_query/django/shorthand.py
odata_query/django/utils.py
odata_query/exceptions.py
odata_query/grammar.py
odata_query/py.typed
odata_query/rewrite.py
odata_query/roundtrip.py
odata_query/sql/__init__.py
odata_query/sql/athena.py
odata_query/sql/base.py
odata_query/sql/sqlite.py
odata_query/sqlalchemy/__init__.py
odata_query/sqlalchemy/common.py
odata_query/sqlalchemy/core.py
odata_query/sqlalchemy/functions_ext.py
odata_query/sqlalchemy/orm.py
odata_query/sqlalchemy/shorthand.py
odata_query/typing.py
odata_query/utils.py
odata_query/visitor.py
odata_query-0.10.0.dist-info/LICENSE
odata_query-0.10.0.dist-info/METADATA
odata_query-0.10.0.dist-info/WHEEL
odata_query-0.10.0.dist-info/RECORD
