Metadata-Version: 2.1
Name: odata-query
Version: 0.10.0
Summary: An OData query parser and transpiler.
License: MIT
Keywords: OData,Query,Parser
Author: Oliver Hofkens
Author-email: oliver@gorilla.co
Requires-Python: >=3.7,<4.0
Classifier: Development Status :: 5 - Production/Stable
Classifier: Environment :: Web Environment
Classifier: Framework :: Django
Classifier: Intended Audience :: Developers
Classifier: License :: OSI Approved :: MIT License
Classifier: Operating System :: OS Independent
Classifier: Programming Language :: Python :: 3
Classifier: Programming Language :: Python :: 3.7
Classifier: Programming Language :: Python :: 3.8
Classifier: Programming Language :: Python :: 3.9
Classifier: Programming Language :: Python :: 3.10
Classifier: Programming Language :: Python :: 3.11
Classifier: Programming Language :: Python :: 3.12
Classifier: Programming Language :: Python :: 3 :: Only
Classifier: Programming Language :: SQL
Classifier: Topic :: Database
Classifier: Topic :: Internet :: WWW/HTTP
Classifier: Topic :: Internet :: WWW/HTTP :: Indexing/Search
Classifier: Topic :: Software Development :: Compilers
Provides-Extra: dev
Provides-Extra: django
Provides-Extra: docs
Provides-Extra: linting
Provides-Extra: sqlalchemy
Provides-Extra: testing
Requires-Dist: black (>=22.1,<23.0) ; extra == "linting"
Requires-Dist: bump2version (>=1.0,<2.0) ; extra == "dev"
Requires-Dist: django (>=2.2) ; extra == "django"
Requires-Dist: flake8 (>=3.8,<4.0) ; extra == "linting"
Requires-Dist: isort (>=5.7,<6.0) ; extra == "linting"
Requires-Dist: mypy (>=0.931,<0.932) ; extra == "linting"
Requires-Dist: pytest (>=6.2,<8.0) ; extra == "testing"
Requires-Dist: pytest-cov ; extra == "testing"
Requires-Dist: python-dateutil (>=2.8.1,<3.0.0)
Requires-Dist: sly (>=0.4,<0.5)
Requires-Dist: sphinx (>=5.3,<6.0) ; extra == "docs"
Requires-Dist: sphinx-rtd-theme (>=2.0,<3.0) ; extra == "docs"
Requires-Dist: sqlalchemy (>=1.4,<2.0) ; extra == "sqlalchemy"
Requires-Dist: types-python-dateutil (>=2.8.1,<3.0.0) ; extra == "linting"
Requires-Dist: vulture (>=2.3,<3.0) ; extra == "linting"
